daqx/__init__ .py
daqx/basedaq.py
daqx/mccdaq.py
daqx/util.py
daqx-0.0.2.dist-info/LICENSE
daqx-0.0.2.dist-info/METADATA
daqx-0.0.2.dist-info/WHEEL
daqx-0.0.2.dist-info/top_level.txt
daqx-0.0.2.dist-info/RECORD
