Metadata-Version: 2.1
Name: daqx
Version: 0.0.2
Summary: Python data acquisition toolbox - MCC
Project-URL: Homepage, https://github.com/wtmtmw/daqx
Keywords: acquisition,mcc
Classifier: Programming Language :: Python :: 3
Classifier: License :: OSI Approved :: MIT License
Classifier: Operating System :: Microsoft :: Windows
Requires-Python: >=3.10
License-File: LICENSE
Requires-Dist: mcculw
Requires-Dist: numpy
